LICENSE
README.md
pyproject.toml
src/celeries/__init__.py
src/celeries/birkhoff.py
src/celeries/ellipseries.py
src/celeries/laplace.py
src/celeries/mmr.py
src/celeries/mpfrac.py
src/celeries/perham.py
src/celeries/perham3pla.py
src/celeries/prime.py
src/celeries/series.py
src/celeries.egg-info/PKG-INFO
src/celeries.egg-info/SOURCES.txt
src/celeries.egg-info/dependency_links.txt
src/celeries.egg-info/requires.txt
src/celeries.egg-info/top_level.txt
tests/test_mmr.py
tests/test_perham.py
tests/test_perham3pla.py